LICENSE
README.md
setup.cfg
setup.py
django_kn_defaults.egg-info/PKG-INFO
django_kn_defaults.egg-info/SOURCES.txt
django_kn_defaults.egg-info/dependency_links.txt
django_kn_defaults.egg-info/requires.txt
django_kn_defaults.egg-info/top_level.txt
kn_defaults/__init__.py
kn_defaults/logging/__init__.py
kn_defaults/logging/app_settings.py
kn_defaults/logging/apps.py
kn_defaults/logging/checks.py
kn_defaults/logging/decorators.py
kn_defaults/logging/defaults.py
kn_defaults/logging/handlers.py
kn_defaults/logging/middlewares.py
kn_defaults/utils/__init__.py
kn_defaults/utils/middlewares.py
kn_defaults/utils/misc.py
kn_defaults/utils/validators.py
tests/__init__.py
tests/test_settings.py
tests/tests.py
tests/urls.py